outlier_101703382.py
outlier_101703382-1.0.0.data/scripts/outliers_cli
outlier_101703382-1.0.0.dist-info/METADATA
outlier_101703382-1.0.0.dist-info/WHEEL
outlier_101703382-1.0.0.dist-info/top_level.txt
outlier_101703382-1.0.0.dist-info/RECORD
