Metadata-Version: 2.1
Name: outlier-101703382
Version: 1.0.0
Summary: Outlier Removal Using Z-score or IQR
Home-page: UNKNOWN
Author: Paras Arora
Author-email: parora_be17@thapar.edu
License: UNKNOWN
Keywords: command-line,Outliers,outlier-removal,row-removal
Platform: UNKNOWN
Classifier: Programming Language :: Python :: 3
Classifier: License :: OSI Approved :: MIT License
Classifier: Operating System :: OS Independent
Requires-Python: >=3.6
Requires-Dist: numpy
Requires-Dist: pandas
